setup_tool/__init__.py
setup_tool/conf/__init__.py
setup_tool/management/__init__.py
setup_tool/management/apps.py
setup_tool/management/commands/__init__.py
setup_tool/management/commands/prettystartapp.py
setup_tool/management/commands/prettystartproject.py
tests/__init__.py
django_setup_tool-0.0.10.dist-info/LICENSE
django_setup_tool-0.0.10.dist-info/METADATA
django_setup_tool-0.0.10.dist-info/WHEEL
django_setup_tool-0.0.10.dist-info/entry_points.txt
django_setup_tool-0.0.10.dist-info/top_level.txt
django_setup_tool-0.0.10.dist-info/RECORD
